{
  "1505400001": {
    "korean": "자유롭고 대지의 축복이 가득한 세계, 미드가르드.",
    "english": "A world of freedom, blessed by the earth—Midgard."
  },
  "1505400002": {
    "korean": "풍요로움이 가득한 이 대지에서 인간들은 큰 번영을 이루었다.",
    "english": "In this abundant land, humanity achieved great prosperity."
  },
  "1505400003": {
    "korean": "인간들은 축복받은 대지에서 미드가르드의 그 어떤 종족들보다 수많은 업적을 쌓아 올렸고.",
    "english": "Humans built countless achievements on the blessed soil, surpassing any other race of Midgard."
  },
  "1505400004": {
    "korean": "사람들은 자신들이 일궈낸 업적들을 드높게 찬양하고 노래했다.",
    "english": "People sang praises, glorifying the feats they had forged."
  },
  "1505400005": {
    "korean": "미드가르드 제일의 종족으로서 그리고 축복받은 대지의 주인으로서, 인간의 영광스러운 번영이 영원히 계속되리라 믿었다.",
    "english": "As the foremost race of Midgard and masters of the blessed earth, they believed humanity’s glorious prosperity would endure forever."
  },
  "1505400006": {
    "korean": "하지만…",
    "english": "But…"
  },
  "1505400007": {
    "korean": "영원히 계속되리라 믿었던 영광이 산산이 부서지는 데에는, 그리 오래 걸리지 않았다.",
    "english": "It didn’t take long for that everlasting glory they trusted in to shatter to pieces."
  },
  "1505400008": {
    "korean": "대지의 축복 속에 인간들이 쌓아 올린 업적들은…",
    "english": "The achievements humanity piled up under the earth’s blessings…"
  },
  "1505400009": {
    "korean": "어떤 존재들의 등장으로 한순간에 불타올라 모두 잿더미가 되었다.",
    "english": "…were suddenly ignited by the arrival of certain beings, reduced to ash."
  },
  "1505400010": {
    "korean": "미드가르드가 아닌 다른 세계에서 경계를 넘어온 존재…",
    "english": "A being that crossed the border from a world beyond Midgard…"
  },
  "1505400011": {
    "korean": "「악룡」",
    "english": "“The Evil Dragon”"
  },
  "1505400012": {
    "korean": "악룡의 등장은 인간들에게 있어서 하늘로부터 내려온 재앙 그 자체였다.",
    "english": "The dragon’s arrival was a disaster sent straight from the heavens for humanity."
  },
  "1505400013": {
    "korean": "악룡은 무자비하게 인간들을 공격했고, 풍요와 축복이 가득한 대지는 붉게 타오르는 대지로 뒤바뀌었다.",
    "english": "The dragon mercilessly attacked humans, turning the once fertile, blessed land into a burning, scarlet wasteland."
  },
  "1505400014": {
    "korean": "인간들은 힘을 모아 악룡들에게 반격했지만, 압도적인 힘의 차이에 속수무책으로 당할 수밖에 없었다.",
    "english": "Humanity gathered their strength to strike back, but the overwhelming power gap left them helpless."
  },
  "1505400015": {
    "korean": "그렇게 인간들의 찬란한 영광은, 미드가르드의 역사 중 하나가 되어 기억의 저편으로 사라질 운명에 처했다.",
    "english": "Thus, humanity’s radiant glory was doomed to become just another footnote in Midgard’s history, fading into oblivion."
  },
  "1505400016": {
    "korean": "하지만, 그 절망의 운명은... 돌연히 나타난 한 줄기의 희망에 의해 구원을 받았다.",
    "english": "Yet that fate of despair was… saved by a sudden ray of hope."
  },
  "1505400017": {
    "korean": "악룡으로부터 미드가르드를 지키기 위해 일어선 한 명의 아이.",
    "english": "A lone child who rose to protect Midgard from the dragon."
  },
  "1505400018": {
    "korean": "아이는 불타오르는 대지를 보며, 자신의 손으로 미드가르드를 원래의 아름다웠던 모습으로 되돌리겠다고 다짐했다.",
    "english": "Seeing the burning land, the child swore to restore Midgard to its former beauty with their own hands."
  },
  "1505400019": {
    "korean": "그리고 아이는 수많은 악룡들을 처단하였고, 많은 사람에게 희망을 안겨주었다.",
    "english": "And the child slew countless dragons, bringing hope to many."
  },
  "1505400020": {
    "korean": "사람들은 악룡을 쓰러트리는 아이의 모습을 보며 모두가 이렇게 불렀다.",
    "english": "Watching the child defeat the dragons, the people all cried out together."
  },
  "1505400021": {
    "korean": "용살자『드래곤 슬레이어』 라고…",
    "english": "“Dragon Slayer”…"
  }
}