{
  "1002702599": {
    "korean": "확산 포격",
    "english": "Spread Bombardment"
  },
  "1002702600": {
    "korean": "클러스터 캐논",
    "english": "Cluster Cannon"
  },
  "1002702601": {
    "korean": "설원 위장",
    "english": "Snow Camouflage"
  },
  "1002702602": {
    "korean": "포신 급속 냉각",
    "english": "Rapid Barrel Cooling"
  },
  "1002702603": {
    "korean": "클러스터 캐논 (착탄)",
    "english": "Cluster Cannon (Impact)"
  },
  "1002704425": {
    "korean": "포격으로 지정 범위에 {0} 피해를 줍니다. 대상이 회피 / 방어력 감소 상태면 피해량이 증가합니다.",
    "english": "Deals {0} damage to the designated area with a bombardment. Damage increases if the target is EVA / Marked / Rooted."
  },
  "1002704426": {
    "korean": "1라운드 뒤에 착탄하는 포격으로 지정 범위에 {0} 보호 무시 피해를 줍니다. 목표 지점은 50% 피해만 줍니다. 대상이 표식 / 이동 불가 상태면 피해량이 증가합니다.",
    "english": "A bombardment that lands after 1 round deals {0} Ignore Protection damage to the designated area. The target point deals only 50% damage. Damage increases if the target is Marked / Rooted."
  },
  "1002704427": {
    "korean": "냉기 속성 저항이 증가하며, <혹한> 효과를 받는 상태에선 방어력 / 효과 저항이 증가합니다.",
    "english": "Cold Resist increases, and while in <Extreme Cold> state, DEF / Status Resist increase."
  },
  "1002704428": {
    "korean": "공격 후, 포신을 냉각해 3라운드 동안 행동력이 증가합니다.",
    "english": "After attacking, cool the barrel to increase SPD for 3 rounds."
  },
  "1002704429": {
    "korean": "포격으로 지정 범위에 {0} 보호 무시 피해를 줍니다. 대상이 표식 / 이동 불가 상태면 피해량이 증가합니다.",
    "english": "Deals {0} Ignore Protection damage to the designated area with a bombardment. Damage increases if the target is Marked / Rooted."
  },
  "1000104028": {
    "korean": "설원 위장 : 방어력{0}%",
    "english": "Snow camouflage : DEF {0}%"
  },
  "1000104855": {
    "korean": "설원 위장 : 효과 저항{0}%",
    "english": "Snow camouflage : Status Resist {0}%"
  },
  "1000104029": {
    "korean": "포신 급속 냉각 : 행동력{0}%",
    "english": "Rapid cooling of the gun barrel : SPD {0}%"
  }
}