{
  "1002701493": {
    "korean": "점착탄 연사",
    "english": "Sticky Grenade Barrage"
  },
  "1002701494": {
    "korean": "정밀 선도 사격",
    "english": "Precision Lead Shot"
  },
  "1002701495": {
    "korean": "위장 홀로그램 투영",
    "english": "Camouflage Hologram Projection"
  },
  "1002701496": {
    "korean": "저격 대응",
    "english": "Sniper Counter"
  },
  "1002704118": {
    "korean": "점착탄을 연사해 {0} 피해를 주고, 대상들의 회피를 낮추며 회피 강화 효과를 해제합니다. 적중 대상은 행동력이 감소하며, 자신은 적중과 사거리가 증가합니다. 해당 효과는 2회까지 중첩됩니다.",
    "english": "Fires a barrage of sticky grenades dealing {0} damage, lowers enemies' EVA and removes EVA buffs. Affected targets have their SPD reduced, while you gain increased ACC and Range. Stacks up to 2 times."
  },
  "1002704119": {
    "korean": "정밀 선도 사격으로 {0} 방어 관통 피해를 줍니다. 대상이 기동형인 경우, 피해량이 크게 증가합니다.",
    "english": "Deals {0} DEF Penetration damage with Precision Lead Shot. If the target is mobile, damage is greatly increased."
  },
  "1002704120": {
    "korean": "위장 홀로그램을 투영해, 적 진영과 멀수록 회피가 증가합니다. 해당 효과는 공격 시, 해당 라운드에는 일시적으로 해제됩니다.",
    "english": "Projects a camouflage hologram that increases EVA the farther you are from the enemy camp. This effect is temporarily removed for the round when you attack."
  },
  "1002704121": {
    "korean": "피격 시, 재빠르게 대응해 행동력이 증가하며 반격합니다. 행동력 증가 효과는 3회까지 중첩됩니다.",
    "english": "When hit, quickly respond, increasing SPD and counterattacking. SPD increase stacks up to 3 times."
  },
  "1000103295": {
    "korean": "점착탄 연사 : 회피 {0}%",
    "english": "Sticky grenade rapid fire : EVA {0}%"
  },
  "1000104564": {
    "korean": "점착탄 연사 : 강화 효과 해제",
    "english": "Sticky grenade rapid fire : Buff Removal"
  },
  "1000103301": {
    "korean": "점착탄 연사 : 행동력 {0}%",
    "english": "Sticky grenade rapid fire : SPD {0}%"
  },
  "1000103299": {
    "korean": "점착탄 연사 : 적중{0}%",
    "english": "Sticky grenade rapid fire : ACC {0}%"
  },
  "1000103302": {
    "korean": "점착탄 연사 : 사거리{0}%",
    "english": "Sticky grenade rapid fire : Range {0}%"
  },
  "1000103296": {
    "korean": "정밀 선도 사격 : 피해량{0}%",
    "english": "Precision leading shooting : Additional DMG {0}%"
  },
  "1000103300": {
    "korean": "정밀 선도 사격 : 방어 관통{0}%",
    "english": "Precision leading shooting : DEF Penetration {0}%"
  },
  "1000103297": {
    "korean": "위장 홀로그램 투영 : 회피{0}%",
    "english": "Camouflage holographic projection : EVA {0}%"
  },
  "1000103298": {
    "korean": "대응 사격 : 행동력{0}%",
    "english": "Counter Shot : SPD {0}%"
  },
  "1000103126": {
    "korean": "대응 사격 : {0}% 위력으로 반격",
    "english": "Counter Shot : Counter Attack with {0}% Power"
  }
}