{
  "1000103541": {
    "korean": "너클 버스터 : HP 낮을수록 피해량{0}% (최대)",
    "english": "Knuckle Buster : Damage increases up to {0}% as HP decreases (max)"
  },
  "1000107569": {
    "korean": "보호 모드 해제",
    "english": "Protection Mode Release"
  },
  "1000107567": {
    "korean": "개량형 방어 OS : 방어력{0}%",
    "english": "Improved Defense OS : DEF {0}%"
  },
  "1000107665": {
    "korean": "개량형 방어 OS : 효과 저항{0}%",
    "english": "Improved Defense OS : Status Resist {0}%"
  },
  "1000107568": {
    "korean": "보호 모드 : 받는 피해 감소{0}% (1회)",
    "english": "Protection Mode : DMG Reduction {0}% (1x)"
  },
  "1000107615": {
    "korean": "보호 모드 오작동 : 받는 피해{0}%",
    "english": "Protection Mode Malfunction : DMG Taken {0}%"
  }
}