{
  "1002707539": {
    "korean": "태양 숨결",
    "english": "Sun's Breath"
  },
  "1002707540": {
    "korean": "퇴마의 술법",
    "english": "Exorcism"
  },
  "1002707541": {
    "korean": "마를 물리는 신체",
    "english": "Hallowed Body"
  },
  "1002707542": {
    "korean": "신성한 광휘",
    "english": "Sacred Radiance"
  },
  "1002707543": {
    "korean": "창조신의 왼쪽 눈",
    "english": "Left Eye of The Creator God"
  },
  "1002707544": {
    "korean": "목표 지점의 적에게 {0} 화염 피해를 주고, 뒷쪽에는 25%씩 감소된 피해를 줍니다. 3라운드 동안 지속 화염 피해를 입히고 화염 저항을 감소시키며 2라운드 동안 이동 불가 상태로 만듭니다.",
    "english": "Deal {0} Fire DMG to enemies at the target location, and enemies behind take 25% reduced damage. Apply Fire DoT DMG for 3 rounds, reduce Fire Resist, and Root for 2 rounds."
  },
  "1002707549": {
    "korean": "목표 지점 대상 {0} 화염 피해 / 지속 화염 피해 / 화염 저항 감소 / 이동 불가",
    "english": "{0} Fire DMG to targets at the target location / Fire DoT DMG / Fire Resist reduction / Rooted"
  },
  "1002707545": {
    "korean": "범위 내 아군에게 냉기 저항을 크게 높여주고 2라운드 동안 유지되는 방어막을 부여합니다. 자신이 버프 범위 내에 포함되었을 경우, [수호부]가 활성화되면서 자신과 범위 내 경장형의 회피가 증가합니다.",
    "english": "Greatly increase Cold Resist and grant a Barrier for 2 rounds to allies in range. If self is within the buff area, activate Guardian Shield, raising EVA of self and Light units in range."
  },
  "1002707550": {
    "korean": "범위 내 아군 냉기 저항 증가 / 방어막 부여 / 자신 수호부 활성화 시, 범위 내 경장 회피 증가",
    "english": "Cold Resist increase for allies in range / Barrier granted / When own Guardian Shield is active, Light EVA increase in range"
  },
  "1002707546": {
    "korean": "라운드 개시 시, 냉기 저항을 증가시키고 받는 피해를 감소시킵니다. 전투 시작 시 AP를 증가시킵니다.",
    "english": "At the start of the round, increase Cold Resist and reduce DMG Taken. At the start of battle, increase AP."
  },
  "1002707551": {
    "korean": "냉기 저항 증가 / 받는 피해 감소 / 전투 시작 시 AP 증가",
    "english": "Cold Resist increase / DMG Reduction / AP increase at battle start"
  },
  "1002707547": {
    "korean": "라운드 시작 시, 범위 내의 아군을 지정 보호하고 아군의 냉기 속성 저항을 증가시킵니다. 추가로 공격기의 공격력, 지원기의 행동력을 증가시킵니다.",
    "english": "At the start of the round, grant Target Protect to allies in range and increase Cold Resist. Additionally, increase ATK of Attackers and SPD of Supporters."
  },
  "1002707552": {
    "korean": "범위 내 아군 지정 보호 / 냉기 저항 증가 / 공격기 공격력 증가 / 지원기 행동력 증가",
    "english": "Target Protect for allies in range / Cold Resist increase / Attacker ATK increase / Supporter SPD increase"
  },
  "1002707548": {
    "korean": "정찰로 다음에 출현할 적을 확인할 수 있습니다. 정찰 활성화된 상태로 전투 시작 시, 자신에게 피해 무효화가 적용됩니다. 전투 시작 시, 적 전체의 효과 저항과 화염 저항을 감소시킵니다.",
    "english": "Recon Effect reveals the next enemy wave. If battle begins while Recon Effect is active, you gain Damage Nullification. At the start of battle, reduce all enemies' Status Resist and Fire Resist."
  },
  "1002707553": {
    "korean": "정찰 / 정찰 활성화 시 자신 피해 무효화 / 적 전체 효과 저항, 화염 저항 감소",
    "english": "Recon Effect / Damage Nullification when Recon Effect active / All enemies' Status Resist, Fire Resist reduction"
  },
  "1000109700": {
    "korean": "퇴마의 술법 : 수호부 활성화(자신)",
    "english": "Exorcism Technique: Activate Guardian Shield (Self)"
  },
  "1000109721": {
    "korean": "가, 가까이 오지 말거라!",
    "english": "D-Don't come any closer!"
  },
  "1000109722": {
    "korean": "너무 배고파…",
    "english": "So hungry…"
  },
  "1000109683": {
    "korean": "태양 숨결 : 지속 화염 피해 {0}",
    "english": "Sun's Breath : Fire DoT DMG {0}"
  },
  "1000109694": {
    "korean": "태양 숨결 : 화염 저항{0}%",
    "english": "Sun's Breath : Fire Resist {0}%"
  },
  "1000109699": {
    "korean": "태양 숨결 : 이동 불가",
    "english": "Sun's Breath : Rooted"
  },
  "1000109684": {
    "korean": "퇴마의 술법 : 냉기 저항{0}%",
    "english": "Exorcism : Cold Resist {0}%"
  },
  "1000109695": {
    "korean": "퇴마의 술법 : 방어막{0}",
    "english": "Exorcism : Barrier {0}"
  },
  "1000109704": {
    "korean": "퇴마의 술법 : 회피{0}%(수호부)",
    "english": "Exorcism : EVA {0}% (Guardian Charm)"
  },
  "1000109701": {
    "korean": "마를 물리는 신체 : AP{0}(전투 시작)",
    "english": "Hallowed Body : AP {0} (At battle start)"
  },
  "1000109686": {
    "korean": "신성한 광휘 : 지정 보호",
    "english": "Sacred Radiance : Target Protect"
  },
  "1000109697": {
    "korean": "신성한 광휘 : 공격력{0}%(공격기)",
    "english": "Sacred Radiance : ATK {0}% (Attacker)"
  },
  "1000109702": {
    "korean": "신성한 광휘 : 행동력{0}%(지원기)",
    "english": "Sacred Radiance : SPD {0}% (Supporter)"
  },
  "1000109698": {
    "korean": "창조신의 왼쪽 눈 : 화염 저항{0}%",
    "english": "Left Eye of The Creator God : Fire Resist {0}%"
  },
  "1000109703": {
    "korean": "창조신의 왼쪽 눈 : 정찰 활성화(자신)",
    "english": "Left Eye of The Creator God : Recon Effect (Self)"
  },
  "1000109705": {
    "korean": "창조신의 왼쪽 눈 : 피해 무효화 {0}회(정찰시/자신)",
    "english": "Left Eye of The Creator God : Damage Nullification {0}x (On Recon/Self)"
  }
}